uncertain_variables/__init__.py
uncertain_variables/distributions.py
uncertain_variables/polysys.py
uncertain_variables/variable.py
uncertain_variables/variable_set.py
uncertain_variables-0.1.4.dist-info/licenses/LICENSE
uncertain_variables-0.1.4.dist-info/METADATA
uncertain_variables-0.1.4.dist-info/WHEEL
uncertain_variables-0.1.4.dist-info/top_level.txt
uncertain_variables-0.1.4.dist-info/RECORD
