Metadata-Version: 2.4
Name: uncertain_variables
Version: 0.1.4
Summary: Defining and handling variable sets with probability distributions for surrogate modelling and uncertainty quantification applications
Home-page: https://github.com/TRACE-Structures/uncertain_variables/
Author: András Urbanics, Bence Popovics, Emese Vastag, Elmar Zander, Noémi Friedman
Author-email: popbence@hun-ren.sztaki.hu
Classifier: Programming Language :: Python :: 3
Classifier: License :: OSI Approved :: GNU General Public License v3 (GPLv3)
Classifier: Operating System :: OS Independent
Classifier: Development Status :: 3 - Alpha
License-File: LICENSE
Requires-Dist: numpy
Requires-Dist: scikit-learn
Requires-Dist: scipy
Requires-Dist: matplotlib
Requires-Dist: SALib
Requires-Dist: pint
Dynamic: author
Dynamic: author-email
Dynamic: classifier
Dynamic: description
Dynamic: description-content-type
Dynamic: home-page
Dynamic: license-file
Dynamic: requires-dist
Dynamic: summary
